metrima/__init__.py
metrima/lib.py
metrima/tests.py
metrima/core/__init__.py
metrima/core/constant.py
metrima/core/fixed.py
metrima/core/temporary.py
metrima/math/__init__.py
metrima/math/constants.py
metrima/math/main.py
metrima/units/__init__.py
metrima/units/time.py
metrima/units/utils.py
metrima/units/weight.py
metrima/utils/__init__.py
metrima/utils/center_text.py
metrima/utils/decorators.py
metrima/utils/errors.py
metrima/utils/exists.py
metrima-0.3.5.3.dist-info/licenses/LICENSE
metrima-0.3.5.3.dist-info/METADATA
metrima-0.3.5.3.dist-info/WHEEL
metrima-0.3.5.3.dist-info/entry_points.txt
metrima-0.3.5.3.dist-info/top_level.txt
metrima-0.3.5.3.dist-info/RECORD
