Metadata-Version: 2.4
Name: metrima
Version: 0.3.5.3
Summary: Just another (cool) no-deps math library
Author-email: Razka Rizaldi <razka.rizaldis@gmail.com>, tyydev1 <torchist@proton.me>
License-Expression: MIT
Project-URL: Homepage, https://github.com/tyydev1/metrima
Project-URL: Repository, https://github.com/tyydev1/metrima
Project-URL: Issues, https://github.com/tyydev1/metrima/issues
Keywords: math,mathematics,library
Classifier: Development Status :: 3 - Alpha
Classifier: Intended Audience :: Developers
Classifier: Programming Language :: Python :: 3
Classifier: Programming Language :: Python :: 3.8
Classifier: Programming Language :: Python :: 3.9
Classifier: Programming Language :: Python :: 3.10
Classifier: Programming Language :: Python :: 3.11
Classifier: Programming Language :: Python :: 3.12
Requires-Python: >=3.10
License-File: LICENSE
Requires-Dist: tinycolors>=0.6.1
Requires-Dist: typing-extensions>=4.15.0
Provides-Extra: dev
Requires-Dist: pytest>=7.0.0; extra == "dev"
Requires-Dist: black>=23.0.0; extra == "dev"
Requires-Dist: mypy>=1.0.0; extra == "dev"
Requires-Dist: sphinx>=8.1.3; extra == "dev"
Requires-Dist: furo>=2025.9.25; extra == "dev"
Requires-Dist: sphinx-autoapi>=3.6.1; extra == "dev"
Dynamic: license-file
